bioread/__init__.py
bioread/_metadata.py
bioread/biopac.py
bioread/file_revisions.py
bioread/headers.py
bioread/reader.py
bioread/struct_dict.py
bioread/runners/__init__.py
bioread/runners/acq2hdf5.py
bioread/runners/acq2mat.py
bioread/runners/acq2txt.py
bioread/runners/acq_info.py
bioread/runners/acq_markers.py
bioread/writers/__init__.py
bioread/writers/matlabwriter.py
bioread/writers/txtwriter.py
meng_bioread-3.0.2.dist-info/LICENSE
meng_bioread-3.0.2.dist-info/METADATA
meng_bioread-3.0.2.dist-info/WHEEL
meng_bioread-3.0.2.dist-info/entry_points.txt
meng_bioread-3.0.2.dist-info/top_level.txt
meng_bioread-3.0.2.dist-info/RECORD
