Metadata-Version: 2.1
Name: meng-bioread
Version: 3.0.2
Summary: A modified version of bioread
Home-page: https://github.com/uwmadison-chm/bioread
Author: Nate Vack
Author-email: njvack@wisc.edu
Maintainer: Nate Vack
Maintainer-email: njvack@wisc.edu
License: MIT
Download-URL: https://github.com/uwmadison-chm/bioread/releases
Keywords: science research physiological biopac convert library
Platform: OS Independent
Classifier: Development Status :: 5 - Production/Stable
Classifier: Environment :: Console
Classifier: Intended Audience :: Developers
Classifier: Intended Audience :: Science/Research
Classifier: License :: OSI Approved :: MIT License
Classifier: Natural Language :: English
Classifier: Operating System :: OS Independent
Classifier: Programming Language :: Python
Classifier: Topic :: Scientific/Engineering :: Information Analysis
Provides: bioread
License-File: LICENSE
Requires-Dist: numpy
Requires-Dist: docopt (>=0.6.1)
Provides-Extra: all
Requires-Dist: scipy ; extra == 'all'
Requires-Dist: h5py ; extra == 'all'
Provides-Extra: hdf5
Requires-Dist: h5py ; extra == 'hdf5'
Provides-Extra: mat
Requires-Dist: scipy ; extra == 'mat'
